README
setup.py
memcache_clone/__init__.py
memcache_clone/memcache_clone.py
memcache_clone.egg-info/PKG-INFO
memcache_clone.egg-info/SOURCES.txt
memcache_clone.egg-info/dependency_links.txt
memcache_clone.egg-info/top_level.txt
memcache_clone.egg-info/zip-safe