Metadata-Version: 1.1
Name: memcache-clone
Version: 1.0.3
Summary: Clone memcache data to othor memcahe .
Home-page: https://github.com/freelingchang/memcache_clone
Author: lingchang
Author-email: freelingchang@email.com
License: MIT
Keywords: memcache clone package
Platform: UNKNOWN
Classifier: License :: OSI Approved :: MIT License
Classifier: Programming Language :: Python
Classifier: Intended Audience :: Developers
Classifier: Operating System :: OS Independent
